{
  "dt.patient": ["SELECT\n\tDATA ->> 'id'\tAS\t\"patient_identifier_value\"\nFROM\n\tresources\nWHERE\n  type = 'Patient'\nORDER BY\n\tdata ->> 'id';"],
  "dt.gender": ["SELECT\n\tDATA ->> 'gender'\tAS\t\"patient_gender\",\nDATA ->> 'id'\tAS\t\"patient_identifier_value\"\nFROM\n\tresources\nWHERE\n  type = 'Patient'\nORDER BY\n\tdata ->> 'id';"],
  "dt.zipcode": ["SELECT\n\tDATA ->> 'id'\tAS\t\"patient_identifier_value\",\nDATA -> 'address' -> 0 ->> 'postalCode'\tAS\t\"patient_address_postalCode\"\nFROM\n\tresources\nWHERE\n  type = 'Patient'\nORDER BY\n\tdata ->> 'id';"],
  "dt.birthdate": ["SELECT\n\tDATA ->> 'birthDate'\tAS\t\"patient_birthDate\",\nDATA ->> 'id'\tAS\t\"patient_identifier_value\"\nFROM\n\tresources\nWHERE\n  type = 'Patient'\nORDER BY\n\tdata ->> 'id';"],
  "dt.encounter": ["SELECT\n\tREPLACE(DATA ->> 'id', 'Patient/', '')\tAS\t\"encounter_identifier_value\",\nREPLACE(DATA -> 'subject' ->> 'reference', 'Patient/', '')\tAS\t\"encounter_subject_patient_identifier_value\"\nFROM\n\tresources\nWHERE\n  type = 'Encounter';"],
  "dt.encounterstart": ["SELECT\n  DATA ->> 'id'\tAS\t\"encounter_identifier_value\",\n  TO_DATE(DATA -> 'period' ->> 'start', 'YYYY-MM-DD')\tAS\t\"encounter_period_start\"\nFROM\n\tresources\nWHERE\n  type = 'Encounter'\nORDER BY\n  DATA ->>'id';"],
  "dt.encounterend": ["SELECT\n  DATA ->> 'id'\tAS\t\"encounter_identifier_value\",\n  TO_DATE(DATA -> 'period' ->> 'end', 'YYYY-MM-DD')\tAS\t\"encounter_period_end\"\nFROM\n\tresources\nWHERE\n  type = 'Encounter'\nORDER BY\n  DATA ->>'id';"],
  "dt.condition": ["SELECT\n  REPLACE(DATA -> 'encounter' ->> 'reference', 'Encounter/', '')\tAS\t\"condition_encounter_identifier_value\",\n  DATA -> 'code' -> 'coding' -> 0 ->> 'code'\tAS\t\"condition_code_coding_code\"\nFROM\n\tresources\nWHERE\n  type = 'Condition';"]
}
