{
  "dt.patient": ["SELECT\n\t\"Patientennummer\"\tAS\t\"patient_identifier_value\"\nFROM\n\tp21.fall\nORDER BY\n\t\"Patientennummer\";"],
  "dt.gender": ["SELECT\n\t\"Geschlecht\"\tAS\t\"patient_gender\",\n\"Patientennummer\"\tAS\t\"patient_identifier_value\"\nFROM\n\tp21.fall\nORDER BY\n\t\"Patientennummer\";"],
  "dt.zipcode": ["SELECT\n\t\"KH-internes-Kennzeichen\"\tAS\t\"patient_identifier_value\",\n\"PLZ\"\tAS\t\"patient_address_postalCode\"\nFROM\n\tp21.fall\nORDER BY\n\t\"Patientennummer\";"],
  "dt.birthdate": ["SELECT\n\t\"Geburtsjahr\"\tAS\t\"patient_birthDate\",\n\"Patientennummer\"\tAS\t\"patient_identifier_value\"\nFROM\n\tp21.fall\nORDER BY\n\t\"Patientennummer\";"],
  "dt.encounter": ["SELECT\n\t\"KH-internes-Kennzeichen\"\tAS\t\"encounter_identifier_value\",\n\"Patientennummer\"\tAS\t\"encounter_subject_patient_identifier_value\"\nFROM\n  p21.fall\nORDER BY\n  \"Patientennummer\";"],
  "dt.encounterstart": ["\nSELECT\n  \"KH-internes-Kennzeichen\"\tAS\t\"encounter_identifier_value\",\n  \"Aufnahmedatum\"\tAS\t\"encounter_period_start\"\nFROM\n  p21.fall\nORDER BY\n  \"KH-internes-Kennzeichen\";"],
  "dt.encounterend": ["\nSELECT\n  \"KH-internes-Kennzeichen\"\tAS\t\"encounter_identifier_value\",\n  \"Entlassungsdatum\"\tAS\t\"encounter_period_end\"\nFROM\n  p21.fall\nORDER BY\n  \"KH-internes-Kennzeichen\";"],
  "dt.ageindays": ["\nSELECT\n  \"KH-internes-Kennzeichen\"\tAS\t\"encounter_identifier_value\",\n  \"Alter-in-Tagen-am-Aufnahmetag\"\tAS\t\"encounter_subject_patient_age_days\"\nFROM\n  p21.fall\nORDER BY\n  \"KH-internes-Kennzeichen\";"],
  "dt.ageinyears": ["\nSELECT\n  \"KH-internes-Kennzeichen\"\tAS\t\"encounter_identifier_value\",\n  \"Alter-in-Jahren-am-Aufnahmetag\"\tAS\t\"encounter_subject_patient_age_years\"\nFROM\n  p21.fall\nORDER BY\n  \"KH-internes-Kennzeichen\";"],
  "dt.admission": ["\nSELECT\n  \"KH-internes-Kennzeichen\"\tAS\t\"encounter_identifier_value\",\n  \"Aufnahmeanlass\"\tAS\t\"encounter_hospitalization_admitSource\"\nFROM\n  p21.fall\nORDER BY\n  \"KH-internes-Kennzeichen\";"],
  "dt.hospitalization": ["\nSELECT\n  \"KH-internes-Kennzeichen\"\tAS\t\"encounter_identifier_value\",\n  \"Aufnahmegrund\"\tAS\t\"encounter_hospitalization_class\"\nFROM\n  p21.fall\nORDER BY\n  \"KH-internes-Kennzeichen\";"],
  "dt.discharge": ["\nSELECT\n  \"KH-internes-Kennzeichen\"\tAS\t\"encounter_identifier_value\",\n  \"Entlassungsgrund\"\tAS\t\"encounter_hospitalization_dischargeDisposition\"\nFROM\n  p21.fall\nORDER BY\n  \"KH-internes-Kennzeichen\";"],
  "dt.ventilation": ["\nSELECT\n  \"KH-internes-Kennzeichen\"\tAS\t\"procedure_encounter_identifier_value\",\n  \"Beatmungsstunden\"\tAS\t\"procedure_code_coding_code_40617009\"\nFROM\n  p21.fall\nORDER BY\n  \"KH-internes-Kennzeichen\";"],
  "dt.condition": ["\nSELECT\n  \"KH-internes-Kennzeichen\"\tAS\t\"condition_encounter_identifier_value\",\n  \"ICD-Kode\"\tAS\t\"condition_code_coding_code\"\nFROM\n  p21.icd\nORDER BY\n  \"KH-internes-Kennzeichen\";"],
  "dt.conditioncategory": ["\nSELECT\n  \"KH-internes-Kennzeichen\"\tAS\t\"condition_encounter_identifier_value\",\n  \"Diagnoseart\"\tAS\t\"encounter_diagnosis_rank\"\nFROM\n  p21.icd\nORDER BY\n  \"KH-internes-Kennzeichen\";"],
  "dt.procedure": ["\nSELECT\n  \"KH-internes-Kennzeichen\"\tAS\t\"procedure_encounter_identifier_value\",\n  \"OPS-Kode\"\tAS\t\"procedure_code_coding_code\"\nFROM\n  p21.ops\nORDER BY\n  \"KH-internes-Kennzeichen\";"],
  "dt.proceduredate": ["\nSELECT\n  \"KH-internes-Kennzeichen\"\tAS\t\"procedure_encounter_identifier_value\",\n  \"OPS-Datum\"\tAS\t\"procedure_performedDateTime\"\nFROM\n  p21.ops\nORDER BY\n  \"KH-internes-Kennzeichen\";"],
  "dt.procedure_medication": ["\nSELECT\n  \"KH-internes-Kennzeichen\"\tAS\t\"procedure_encounter_identifier_value\",\n  \"OPS-Kode\"\tAS\t\"procedure_code_coding_code\"\nFROM\n  p21.ops\nWHERE\n  \"OPS-Kode\" LIKE '6-00%'\nORDER BY\n  \"KH-internes-Kennzeichen\";"],
  "dt.laboratory": ["SELECT\n\t\"loinc_code\"\tAS\t\"observation_code_coding_code\",\n\"case_id\"\tAS\t\"encounter_identifier_value\"\nFROM\n\tlaboratory.laboratory_p21;"],
  "dt.provider": ["\nSELECT\n  \"KH-internes-Kennzeichen\"\tAS\t\"encounter_identifier_value\",\n  \"FAB\"\tAS\t\"location_identifier_value\"\nFROM\n  p21.fab\nORDER BY\n  \"KH-internes-Kennzeichen\";"],
  "dt.providerstart": ["\nSELECT\n  \"KH-internes-Kennzeichen\"\tAS\t\"encounter_identifier_value\",\n  \"FAB-Aufnahmedatum\"\tAS\t\"encounter_location_period_start\"\nFROM\n  p21.fab\nORDER BY\n  \"KH-internes-Kennzeichen\";"],
  "dt.providerend": ["\nSELECT\n  \"KH-internes-Kennzeichen\"\tAS\t\"encounter_identifier_value\",\n  \"FAB-Entlassungsdatum\"\tAS\t\"encounter_location_period_end\"\nFROM\n  p21.fab\nORDER BY\n  \"KH-internes-Kennzeichen\";"]
}
